<annotation verified="yes">
	<folder>AI-argazkiak</folder>
	<filename>IMG_20210416_081046.jpg</filename>
	<path>C:\Users\ikaslea\Pictures\AI-argazkiak\IMG_20210416_081046.jpg</path>
	<source>
		<database>Unknown</database>
	</source>
	<size>
		<width>3000</width>
		<height>4000</height>
		<depth>3</depth>
	</size>
	<segmented>0</segmented>
	<object>
		<name>Tapa</name>
		<pose>Unspecified</pose>
		<truncated>0</truncated>
		<difficult>0</difficult>
		<bndbox>
			<xmin>526</xmin>
			<ymin>2420</ymin>
			<xmax>1340</xmax>
			<ymax>3160</ymax>
		</bndbox>
	</object>
	<object>
		<name>Ardatza</name>
		<pose>Unspecified</pose>
		<truncated>0</truncated>
		<difficult>0</difficult>
		<bndbox>
			<xmin>1306</xmin>
			<ymin>1653</ymin>
			<xmax>1726</xmax>
			<ymax>2066</ymax>
		</bndbox>
	</object>
	<object>
		<name>Roda</name>
		<pose>Unspecified</pose>
		<truncated>0</truncated>
		<difficult>0</difficult>
		<bndbox>
			<xmin>2173</xmin>
			<ymin>2333</ymin>
			<xmax>2733</xmax>
			<ymax>2880</ymax>
		</bndbox>
	</object>
</annotation>
