<annotation verified="yes">
	<folder>AI-argazkiak</folder>
	<filename>IMG_20210416_081440_0CS.jpg</filename>
	<path>C:\Users\ikaslea\Pictures\AI-argazkiak\IMG_20210416_081440_0CS.jpg</path>
	<source>
		<database>Unknown</database>
	</source>
	<size>
		<width>3000</width>
		<height>4000</height>
		<depth>3</depth>
	</size>
	<segmented>0</segmented>
	<object>
		<name>Tapa</name>
		<pose>Unspecified</pose>
		<truncated>0</truncated>
		<difficult>0</difficult>
		<bndbox>
			<xmin>600</xmin>
			<ymin>2486</ymin>
			<xmax>1506</xmax>
			<ymax>3406</ymax>
		</bndbox>
	</object>
	<object>
		<name>Ardatza</name>
		<pose>Unspecified</pose>
		<truncated>0</truncated>
		<difficult>0</difficult>
		<bndbox>
			<xmin>680</xmin>
			<ymin>1206</ymin>
			<xmax>1286</xmax>
			<ymax>1706</ymax>
		</bndbox>
	</object>
	<object>
		<name>Roda</name>
		<pose>Unspecified</pose>
		<truncated>0</truncated>
		<difficult>0</difficult>
		<bndbox>
			<xmin>2013</xmin>
			<ymin>1606</ymin>
			<xmax>2820</xmax>
			<ymax>2420</ymax>
		</bndbox>
	</object>
</annotation>
